fast_geodist-0.4.0.dist-info/METADATA
fast_geodist-0.4.0.dist-info/WHEEL
fast_geodist-0.4.0.dist-info/license_files/LICENSE
fast_geodist/py.typed
fast_geodist/slow.py
fast_geodist/__init__.py
fast_geodist/_fast_geodist.pyd
fast_geodist-0.4.0.dist-info/RECORD
