Metadata-Version: 2.1
Name: fast-geodist
Version: 0.4.0
Classifier: Programming Language :: Python
Classifier: Programming Language :: Python :: 3
Classifier: Programming Language :: Python :: 3 :: Only
Classifier: Programming Language :: Python :: 3.7
Classifier: Programming Language :: Python :: 3.8
Classifier: Programming Language :: Python :: 3.9
Classifier: Programming Language :: Python :: 3.10
Classifier: License :: OSI Approved :: MIT License
Classifier: Operating System :: POSIX :: Linux
Classifier: Operating System :: Microsoft :: Windows
Classifier: Operating System :: MacOS
Classifier: Topic :: Software Development :: Libraries :: Python Modules
Classifier: Typing :: Typed
Requires-Dist: numpy~=1.0
License-File: LICENSE
Summary: An implementation of Haversine distance calculations using Rust and PyO3
Author-email: Martin Black <18327836+mblackgeo@users.noreply.github.com>
Requires-Python: >=3.7
Project-URL: Homepage, https://github.com/mblackgeo/fast-geodist
Project-URL: Repository, https://github.com/mblackgeo/fast-geodist
